<?xml version="1.0" encoding="utf-8"?>
<class id="f2b444fd-b57c-493b-a296-04cf4f30172e" type="Folder" typeId="3407a825-1331-4f3f-89a4-901903ed97ce">
  <name>Settings</name>
  <display>Settings</display>
  <isAbstract>false</isAbstract>
  <genericTypes />
  <isMapped>false</isMapped>
  <parentFolderId>592466da-f8af-4ba3-bdf3-0dfb22df834e</parentFolderId>
  <stereotypes />
  <metadata />
  <childElements>
    <childElement id="c916d6db-62c0-4323-9d32-97282e37a6f0" type="Template Output" typeId="d421c322-7a51-4094-89fa-e5d8a0a97b27">
      <name>Intent.ModuleBuilder.Templates.Settings.ModuleSettingsExtensions</name>
      <display>Intent.ModuleBuilder.Templates.Settings.ModuleSettingsExtensions</display>
      <externalReference>Intent.ModuleBuilder</externalReference>
      <isAbstract>false</isAbstract>
      <genericTypes />
      <isMapped>false</isMapped>
      <parentFolderId>f2b444fd-b57c-493b-a296-04cf4f30172e</parentFolderId>
      <stereotypes />
      <metadata>
        <entry key="status" value="assigned" />
      </metadata>
      <childElements />
    </childElement>
  </childElements>
</class>