<?xml version="1.0" encoding="utf-8"?>
<class id="fb8b4ce6-590a-4692-b7cc-84dc8070cc07" type="Folder" typeId="4d95d53a-8855-4f35-aa82-e312643f5c5f">
  <name>Input</name>
  <display>Input</display>
  <isAbstract>false</isAbstract>
  <sort-children>by-type-then-by-name</sort-children>
  <genericTypes />
  <isMapped>false</isMapped>
  <parentFolderId>b708fafc-7575-4a74-9ab9-2bb1e6611af0</parentFolderId>
  <packageId>b81dbc72-2d16-4f31-9602-2d89115e1827</packageId>
  <packageName>Aryzac.IO.Modules.Nuxt</packageName>
  <stereotypes>
    <stereotype stereotypeDefinitionId="66fd9e66-42c7-4ef9-a778-b68e009272b9" name="Folder Options">
      <addedByDefault>true</addedByDefault>
      <definitionPackageName>Intent.Common.CSharp</definitionPackageName>
      <definitionPackageId>730e1275-0c32-44f7-991a-9619d07ca68d</definitionPackageId>
      <properties>
        <property name="96df2fa6-7361-4e43-9acf-dbcea23b650a" display="Namespace Provider" value="true" isActive="true" />
      </properties>
    </stereotype>
  </stereotypes>
  <metadata />
  <childElements />
</class>